vmrunPacked/__init__.py
vmrunPacked/util.py
vmrunPacked-0.0.6.dist-info/LICENSE
vmrunPacked-0.0.6.dist-info/METADATA
vmrunPacked-0.0.6.dist-info/WHEEL
vmrunPacked-0.0.6.dist-info/top_level.txt
vmrunPacked-0.0.6.dist-info/RECORD
