Metadata-Version: 2.1
Name: vmrunPacked
Version: 0.0.6
Summary: Using vmrun to Control Virtual Machines. VmWare-vmrun execute actions use python
Home-page: UNKNOWN
Author: William
License: MIT
Platform: UNKNOWN
Classifier: Intended Audience :: Developers
Classifier: Intended Audience :: System Administrators
Classifier: Programming Language :: Python :: 3
Classifier: License :: OSI Approved :: MIT License
Classifier: Operating System :: OS Independent
Requires-Python: >=3
License-File: LICENSE
